arango_crud/__init__.py
arango_crud/auths.py
arango_crud/back_off_strategies.py
arango_crud/clusters.py
arango_crud/collection.py
arango_crud/config.py
arango_crud/database.py
arango_crud/document.py
arango_crud/env_config.py
arango_crud/helper.py
arango_crud-1.0.5.dist-info/METADATA
arango_crud-1.0.5.dist-info/WHEEL
arango_crud-1.0.5.dist-info/top_level.txt
arango_crud-1.0.5.dist-info/RECORD
