Metadata-Version: 2.1
Name: arango-crud
Version: 1.0.5
Summary: A wrapper around ArangoDB CRUD HTTP API
Home-page: https://github.com/tjstretchalot/arango_crud
Author: Timothy Moore
Author-email: mtimothy984+pypi@gmail.com
License: UNKNOWN
Platform: UNKNOWN
Classifier: Programming Language :: Python :: 3
Classifier: Operating System :: OS Independent
Requires-Python: >=3.7
Requires-Dist: certifi
Requires-Dist: chardet
Requires-Dist: idna
Requires-Dist: pytypeutils
Requires-Dist: requests
Requires-Dist: urllib3
